hsecscan/__init__.py
hsecscan/__main__.py
hsecscan/hsecscan.db
hsecscan/hsecscan.py
hsecscan/hsecscancmd.py
hsecscan-0.0.1.dist-info/DESCRIPTION.rst
hsecscan-0.0.1.dist-info/METADATA
hsecscan-0.0.1.dist-info/RECORD
hsecscan-0.0.1.dist-info/WHEEL
hsecscan-0.0.1.dist-info/entry_points.txt
hsecscan-0.0.1.dist-info/metadata.json
hsecscan-0.0.1.dist-info/top_level.txt
