Metadata-Version: 2.0
Name: hsecscan
Version: 0.0.1
Summary: A security scanner for HTTP response headers.
Home-page: https://github.com/riramar/hsecscan/blob/master/README.md
Author: Ricardo Iramar dos Santos
Author-email: ricardo.iramar@gmail.com
License: UNKNOWN
Platform: UNKNOWN
Classifier: Programming Language :: Python :: 2.7
Classifier: License :: OSI Approved :: GNU General Public License v2 (GPLv2)
Classifier: Operating System :: OS Independent
